ipyoverlay/__init__.py
ipyoverlay/connection.py
ipyoverlay/container.py
ipyoverlay/utils.py
ipyoverlay/widgets.py
ipyoverlay/vue/connection.vue
ipyoverlay/vue/container.vue
ipyoverlay/vue/context-menu-area.vue
ipyoverlay/vue/context-menu.vue
ipyoverlay/vue/decorated-widget.vue
ipyoverlay/vue/popup-component.vue
ipyoverlay/vue/rawwidget.vue
ipyoverlay-0.2.1.dist-info/LICENSE
ipyoverlay-0.2.1.dist-info/METADATA
ipyoverlay-0.2.1.dist-info/WHEEL
ipyoverlay-0.2.1.dist-info/top_level.txt
ipyoverlay-0.2.1.dist-info/RECORD
