Metadata-Version: 2.2
Name: ipyoverlay
Version: 0.2.1
Summary: IPyWidget wrappers to support rendering widgets on top of other widgets
Home-page: https://github.com/ORNL/ipyoverlay
Author: Nathan Martindale, Jacob Smith, Jason Hite, Scott L. Stewart, Mark Adams, Lisa Linville
Author-email: ipyoverlay-help@ornl.gov
Project-URL: Documentation, https://ornl.github.io/ipyoverlay/latest/index.html
Keywords: widget,details-on-demand,overlay,ipywidget,jupyter
Classifier: Programming Language :: Python :: 3
Classifier: Programming Language :: Python :: 3.9
Classifier: Programming Language :: Python :: 3.10
Classifier: Programming Language :: Python :: 3.11
Classifier: License :: OSI Approved :: BSD License
Classifier: Operating System :: OS Independent
Classifier: Development Status :: 4 - Beta
Classifier: Environment :: Console
Classifier: Intended Audience :: Science/Research
Requires-Python: >=3.9
License-File: LICENSE
Requires-Dist: ipyvuetify
Requires-Dist: ipywidgets
Requires-Dist: matplotlib
Requires-Dist: plotly
Dynamic: author
Dynamic: author-email
Dynamic: classifier
Dynamic: description
Dynamic: description-content-type
Dynamic: home-page
Dynamic: keywords
Dynamic: project-url
Dynamic: requires-dist
Dynamic: requires-python
Dynamic: summary
